che/__init__.py
che/binding.py
che/main.py
che/utils.py
che/intercept/__init__.py
che/intercept/cache.py
che/intercept/chain.py
che/intercept/conversation.py
che/intercept/interceptor.py
che/intercept/markdown.py
che/intercept/request.py
che/intercept/vote.py
gh_copilot_history_export-2.0.0.dist-info/LICENCE
gh_copilot_history_export-2.0.0.dist-info/METADATA
gh_copilot_history_export-2.0.0.dist-info/WHEEL
gh_copilot_history_export-2.0.0.dist-info/entry_points.txt
gh_copilot_history_export-2.0.0.dist-info/top_level.txt
gh_copilot_history_export-2.0.0.dist-info/RECORD
